python_typograf-0.2.0.dist-info/DESCRIPTION.rst
python_typograf-0.2.0.dist-info/METADATA
python_typograf-0.2.0.dist-info/RECORD
python_typograf-0.2.0.dist-info/WHEEL
python_typograf-0.2.0.dist-info/metadata.json
python_typograf-0.2.0.dist-info/top_level.txt
typograf/__init__.py
typograf/settings.py
typograf/setup.py
typograf/urls.py
typograf/utils.py
typograf/views.py
