Metadata-Version: 2.0
Name: python-typograf
Version: 0.2.0
Summary: Типограф Евгения Лепёшкина
Home-page: https://github.com/diveru4i/typograf
Author: Melfi Silver
Author-email: diveru4i@gmail.com
License: LicenseRef-LICENSE
Platform: UNKNOWN
